LICENSE.txt
MANIFEST.in
README.md
pyproject.toml
requirements.txt
setup.py
aiothornode/__init__.py
aiothornode/connector.py
aiothornode/env.py
aiothornode/nodeclient.py
aiothornode/types.py
aiothornode.egg-info/PKG-INFO
aiothornode.egg-info/SOURCES.txt
aiothornode.egg-info/dependency_links.txt
aiothornode.egg-info/requires.txt
aiothornode.egg-info/top_level.txt
test/__init__.py
test/fixtures.py
test/my_test_vault.py
test/test_bank.py
test/test_bond.py
test/test_chain_info.py
test/test_env.py
test/test_int1.py
test/test_lp.py
test/test_tx.py