Metadata-Version: 2.1
Name: aiothornode
Version: 0.1.7
Summary: THORChain node connection library for Python
Home-page: https://github.com/tirinox/aiothornode
Author: Maksim Koltsov
Author-email: delevoper@tirinox.ru
License: MIT
Classifier: Programming Language :: Python :: 3
Classifier: License :: OSI Approved :: MIT License
Classifier: Operating System :: OS Independent
License-File: LICENSE.txt
